{
  "listes": [
    {
      "pourentage": 30.381987799222287,
      "id": "464",
      "elus": [
        {
          "name": "سعاد بن عبد الرحيم"
        },
        {
          "name": "زياد الدولاتي"
        },
        {
          "name": "حليمة القني"
        }
      ],
      "vote": 68131,
      "name": "قائمة حركة النهضة"
    },
    {
      "pourentage": 19.20195497841675,
      "id": "430",
      "elus": [
        {
          "name": "خليل منصف الزاوية"
        },
        {
          "name": "لبنى الجريبي"
        }
      ],
      "vote": 43060,
      "name": "قائمة حزب التكتل الديمقراطي من أجل العمل والحريات"
    },
    {
      "pourentage": 10.834433305982662,
      "id": "446",
      "elus": [
        {
          "name": "عربي عبيد"
        }
      ],
      "vote": 24296,
      "name": "قائمة حزب المؤتمر من أجل الجمهورية"
    },
    {
      "pourentage": 8.3465627341158,
      "id": "259",
      "elus": [
        {
          "name": "أحمد إبراهيم"
        }
      ],
      "vote": 18717,
      "name": "قائمة القطب الديمقراطي الحداثي"
    },
    {
      "pourentage": 5.891245406870964,
      "id": "137",
      "elus": [
        {
          "name": "أحمد نجيب الشابي"
        }
      ],
      "vote": 13211,
      "name": "قائمة الحزب الديمقراطي التقدمي"
    }
  ],
  "circonscription": {
    "nb_sieges": 8,
    "name": "تونس 2 ",
    "code": "112"
  }
}