{
  "listes": [
    {
      "pourentage": 36.12800389859589,
      "id": "464",
      "elus": [
        {
          "name": "صحبي العتيق"
        },
        {
          "name": "آمال غويل"
        },
        {
          "name": "فرجاني الدغمان"
        }
      ],
      "vote": 71170,
      "name": "قائمة حركة النهضة"
    },
    {
      "pourentage": 13.99535011218616,
      "id": "430",
      "elus": [
        {
          "name": "مولدي الرياحي"
        }
      ],
      "vote": 27570,
      "name": "قائمة حزب التكتل الديمقراطي من أجل العمل والحريات"
    },
    {
      "pourentage": 9.036315826877976,
      "id": "446",
      "elus": [
        {
          "name": "عبد العزيز القطي"
        }
      ],
      "vote": 17801,
      "name": "قائمة حزب المؤتمر من أجل الجمهورية"
    },
    {
      "pourentage": 6.963156238261063,
      "id": "259",
      "elus": [
        {
          "name": "محمد العربي فاضل موسى"
        }
      ],
      "vote": 13717,
      "name": "قائمة القطب الديمقراطي الحداثي"
    },
    {
      "pourentage": 5.009797252708204,
      "id": "137",
      "elus": [
        {
          "name": "عصام الشابي"
        }
      ],
      "vote": 9869,
      "name": "قائمة الحزب الديمقراطي التقدمي"
    },
    {
      "pourentage": 3.361016071555479,
      "id": "444",
      "elus": [
        {
          "name": "كريم بوعبدلي"
        }
      ],
      "vote": 6621,
      "name": "قائمة الحزب الليبرالي المغاربي"
    }
  ],
  "circonscription": {
    "nb_sieges": 8,
    "name": "أريانة",
    "code": "120"
  }
}